mindtrace/automation/__init__.py
mindtrace/automation/label_studio/exceptions.py
mindtrace/automation/label_studio/label_studio_api.py
mindtrace/automation/utils/feature_classifier.py
mindtrace/automation/utils/feature_detector.py
mindtrace/automation/utils/feature_extractors.py
mindtrace/automation/utils/feature_models.py
mindtrace/automation/utils/generate_id_config.py
mindtrace_automation-0.8.0.dist-info/licenses/LICENSE
mindtrace_automation-0.8.0.dist-info/METADATA
mindtrace_automation-0.8.0.dist-info/WHEEL
mindtrace_automation-0.8.0.dist-info/top_level.txt
mindtrace_automation-0.8.0.dist-info/RECORD
