Metadata-Version: 2.4
Name: mindtrace-automation
Version: 0.8.0
Summary: Automation for Mindtrace
Author: Mindtrace Team
License-Expression: Apache-2.0
Project-URL: Homepage, https://mindtrace.ai
Project-URL: Repository, https://github.com/mindtrace/mindtrace/blob/main/mindtrace/automation
Classifier: Programming Language :: Python :: 3
Classifier: Programming Language :: Python :: 3.12
License-File: LICENSE
Requires-Dist: mindtrace-core>=0.8.0
Requires-Dist: mindtrace-registry>=0.8.0
Requires-Dist: mindtrace-database>=0.8.0
Requires-Dist: mindtrace-services>=0.8.0
Requires-Dist: mindtrace-datalake>=0.8.0
Requires-Dist: mindtrace-models>=0.8.0
Requires-Dist: mindtrace-cluster>=0.8.0
Requires-Dist: label-studio-sdk>=2.0.4
Dynamic: license-file
